dawg.cp311-win32.pyd
dawg2-0.13.3.dist-info/licenses/AUTHORS.md
dawg2-0.13.3.dist-info/licenses/LICENSE
dawg2-0.13.3.dist-info/METADATA
dawg2-0.13.3.dist-info/WHEEL
dawg2-0.13.3.dist-info/top_level.txt
dawg2-0.13.3.dist-info/RECORD
