Metadata-Version: 2.4
Name: DAWG2
Version: 0.13.3
Summary: Fast and memory efficient DAWG (DAFSA) for Python
Author-email: Mikhail Korobov <kmike84@gmail.com>
Maintainer-email: insolor <insolor@gmail.com>
Project-URL: Homepage, https://github.com/pymorphy2-fork/DAWG/
Project-URL: Changelog, https://github.com/pymorphy2-fork/DAWG/blob/master/CHANGES.md
Classifier: Development Status :: 4 - Beta
Classifier: Intended Audience :: Developers
Classifier: Intended Audience :: Science/Research
Classifier: License :: OSI Approved :: MIT License
Classifier: Programming Language :: Cython
Classifier: Programming Language :: Python
Classifier: Programming Language :: Python :: 3
Classifier: Programming Language :: Python :: 3.9
Classifier: Programming Language :: Python :: 3.10
Classifier: Programming Language :: Python :: 3.11
Classifier: Programming Language :: Python :: 3.12
Classifier: Programming Language :: Python :: 3.13
Classifier: Programming Language :: Python :: 3.14
Classifier: Programming Language :: Python :: Implementation :: CPython
Classifier: Topic :: Software Development :: Libraries :: Python Modules
Classifier: Topic :: Scientific/Engineering :: Information Analysis
Classifier: Topic :: Text Processing :: Linguistic
Requires-Python: >=3.9
License-File: LICENSE
License-File: AUTHORS.md
Dynamic: license-file
